imswitchclient/ImSwitchClient.py
imswitchclient/__init__.py
imswitchclient/client.py
imswitchclient/communicationManager.py
imswitchclient/experimentController.py
imswitchclient/histoscanManager.py
imswitchclient/lasersManager.py
imswitchclient/ledMatrixManager.py
imswitchclient/objectiveController.py
imswitchclient/positionersManager.py
imswitchclient/recordingManager.py
imswitchclient/settingsManager.py
imswitchclient/socketClient.py
imswitchclient/viewManager.py
imswitchclient-0.1.5.dist-info/licenses/LICENSE
imswitchclient-0.1.5.dist-info/METADATA
imswitchclient-0.1.5.dist-info/WHEEL
imswitchclient-0.1.5.dist-info/top_level.txt
imswitchclient-0.1.5.dist-info/RECORD
